{"sections":{"main":{"type":"main-page","disabled":true,"settings":{"padding_top":28,"padding_bottom":28}},"breadcrumb_K8BcEi":{"type":"breadcrumb","name":"Page Title & Breadcrumb","settings":{}},"custom_photo_media_rAAryL":{"type":"custom-photo-media","blocks":{"photo_UL8cyi":{"type":"photo","disabled":true,"settings":{"image":"shopify:\/\/shop_images\/Food-Mech-Award-Molimor.jpg"}},"photo_micmEK":{"type":"photo","settings":{"image":"shopify:\/\/shop_images\/Bhagwan-Mahavir-Award-Molimor_39fece74-3006-4ad3-88f1-96e23b01e027.jpg"}},"photo_wBnrjM":{"type":"photo","settings":{"image":"shopify:\/\/shop_images\/1c83791c-f3e3-4a60-8cb8-a6e64d5af940.jpg"}},"photo_mbpCrb":{"type":"photo","settings":{"image":"shopify:\/\/shop_images\/63ada77f-a1c7-47c2-8bdf-8cabefbd22b9.jpg"}},"photo_TjK4zt":{"type":"photo","settings":{"image":"shopify:\/\/shop_images\/a00889da-45b5-4f43-993e-d6858374d0dc.jpg"}}},"block_order":["photo_UL8cyi","photo_micmEK","photo_wBnrjM","photo_mbpCrb","photo_TjK4zt"],"name":"Tabbed Masonry Gallery","settings":{"heading":"Awards"}},"custom_photo_media_yxT8xp":{"type":"custom-photo-media","blocks":{"photo_mrz4pk":{"type":"photo","settings":{"image":"shopify:\/\/shop_images\/562fb168-2721-4119-b390-976acd892739.jpg"}},"photo_FjNjbW":{"type":"photo","settings":{"image":"shopify:\/\/shop_images\/18df0dfa-6730-426c-b2fe-b541fc2505e0.jpg"}},"photo_EfBHMK":{"type":"photo","settings":{"image":"shopify:\/\/shop_images\/b28b306f-b5f9-49ef-8074-fcfe25651658.jpg"}},"photo_WeTLDU":{"type":"photo","settings":{"image":"shopify:\/\/shop_images\/92eb9614-46a6-4167-95bb-ed32d80d88e2.jpg"}}},"block_order":["photo_mrz4pk","photo_FjNjbW","photo_EfBHMK","photo_WeTLDU"],"custom_css":[],"name":"Tabbed Masonry Gallery","settings":{"heading":"Food Agree Exhibition Feb-23"}},"custom_photo_media_WnnyGM":{"type":"custom-photo-media","blocks":{"photo_gpdJzc":{"type":"photo","settings":{"image":"shopify:\/\/shop_images\/4.jpg"}},"photo_6gmYTk":{"type":"photo","settings":{"image":"shopify:\/\/shop_images\/3.jpg"}},"photo_GqtkPQ":{"type":"photo","settings":{"image":"shopify:\/\/shop_images\/2.jpg"}},"photo_J9DQt9":{"type":"photo","settings":{"image":"shopify:\/\/shop_images\/1.jpg"}}},"block_order":["photo_gpdJzc","photo_6gmYTk","photo_GqtkPQ","photo_J9DQt9"],"name":"Tabbed Masonry Gallery","settings":{"heading":"Food Mech Exhibition March-23"}}},"order":["main","breadcrumb_K8BcEi","custom_photo_media_rAAryL","custom_photo_media_yxT8xp","custom_photo_media_WnnyGM"]}